ssnp/__init__.py
ssnp/beam.py
ssnp/beam.pyi
ssnp/calc.py
ssnp/calc.pyi
ssnp/const.py
ssnp/const.pyi
ssnp/data.py
ssnp/data.pyi
ssnp/funcs.py
ssnp/funcs.pyi
ssnp/utils.py
ssnp/utils.pyi
ssnp-0.0.1.dist-info/LICENSE.txt
ssnp-0.0.1.dist-info/METADATA
ssnp-0.0.1.dist-info/WHEEL
ssnp-0.0.1.dist-info/top_level.txt
ssnp-0.0.1.dist-info/RECORD
