Metadata-Version: 2.1
Name: ssnp
Version: 0.0.1
Summary: Split-step non-paraxial beam propagation simulation package
Home-page: https://github.com/bu-cisl/ssnp
Author: Jiabei Zhu
Author-email: zjb@bu.edu
License: UNKNOWN
Keywords: simulation,optical engineering,beam propagation method
Platform: UNKNOWN
Classifier: Programming Language :: Python :: 3
Classifier: License :: OSI Approved :: GNU General Public License v3 (GPLv3)
Classifier: Operating System :: OS Independent
Requires-Python: >=3.6
Requires-Dist: tifffile (>=2020)
Requires-Dist: imagecodecs (>=2020)
Requires-Dist: numpy
Requires-Dist: reikna (>=0.7.5)
Requires-Dist: pycuda (==2019.1.2)
Requires-Dist: scipy (>=1.5)
